knok_knok/__init__.py
knok_knok/config.py
knok_knok/fcm.py
knok_knok/utils.py
knok_knok-0.0.1.dist-info/LICENSE
knok_knok-0.0.1.dist-info/METADATA
knok_knok-0.0.1.dist-info/WHEEL
knok_knok-0.0.1.dist-info/top_level.txt
knok_knok-0.0.1.dist-info/RECORD
