Metadata-Version: 2.1
Name: knok-knok
Version: 0.0.1
Summary: For sending push notifications to android and ios devices
Home-page: https://github.com/AjaySharma132/knok_knok
Author: Ajay Sharma
Author-email: ajaysh4rma132@gmail.com
Keywords: push,notifications,android,ios,fcm,gcm
Classifier: Development Status :: 5 - Production/Stable
Classifier: Intended Audience :: Developers
Classifier: Programming Language :: Python :: 2.7
Classifier: Programming Language :: Python :: 3.0
Classifier: Programming Language :: Python :: 3.1
Classifier: Programming Language :: Python :: 3.2
Classifier: Programming Language :: Python :: 3.3
Classifier: Programming Language :: Python :: 3.4
Classifier: Programming Language :: Python :: 3.5
Classifier: Programming Language :: Python :: 3.6
Classifier: Programming Language :: Python :: 3.7
Classifier: Programming Language :: Python :: 3.8
Classifier: Programming Language :: Python :: 3.9
Classifier: Programming Language :: Python :: 3.10
Classifier: Programming Language :: Python :: 3.11
Classifier: Programming Language :: Python :: 3.12
Classifier: License :: OSI Approved :: MIT License
Classifier: Operating System :: OS Independent
Classifier: Topic :: Communications
Classifier: Topic :: Software Development :: Libraries
License-File: LICENSE
Requires-Dist: requests
